<annotation>
  <folder>fullTrainingDataset/batch1</folder>
  <filename>000133.jpg</filename>
  <segmented>0</segmented>
  <size>
    <width>1200</width>
    <height>583</height>
    <depth>3</depth>
  </size>
  <object>
    <name>all_Season_Road</name>
    <pose>Unspecified</pose>
    <truncated>0</truncated>
    <difficult>0</difficult>
    <bndbox>
      <xmin>1021</xmin>
      <ymin>237</ymin>
      <xmax>1196</xmax>
      <ymax>338</ymax>
    </bndbox>
  </object>
  <object>
    <name>all_Season_Road</name>
    <pose>Unspecified</pose>
    <truncated>0</truncated>
    <difficult>0</difficult>
    <bndbox>
      <xmin>842</xmin>
      <ymin>199</ymin>
      <xmax>965</xmax>
      <ymax>254</ymax>
    </bndbox>
  </object>
  <object>
    <name>all_Season_Road</name>
    <pose>Unspecified</pose>
    <truncated>0</truncated>
    <difficult>0</difficult>
    <bndbox>
      <xmin>752</xmin>
      <ymin>323</ymin>
      <xmax>1036</xmax>
      <ymax>579</ymax>
    </bndbox>
  </object>
</annotation>
