<annotation>
  <folder>fullTrainingDataset/batch2</folder>
  <filename>000253.jpg</filename>
  <segmented>0</segmented>
  <size>
    <width>900</width>
    <height>1200</height>
    <depth>3</depth>
  </size>
  <object>
    <name>all_Season_Road</name>
    <pose>Unspecified</pose>
    <truncated>0</truncated>
    <difficult>0</difficult>
    <bndbox>
      <xmin>18</xmin>
      <ymin>961</ymin>
      <xmax>308</xmax>
      <ymax>1199</ymax>
    </bndbox>
  </object>
  <object>
    <name>all_Season_Road</name>
    <pose>Unspecified</pose>
    <truncated>0</truncated>
    <difficult>0</difficult>
    <bndbox>
      <xmin>23</xmin>
      <ymin>837</ymin>
      <xmax>132</xmax>
      <ymax>959</ymax>
    </bndbox>
  </object>
  <object>
    <name>all_Season_Road</name>
    <pose>Unspecified</pose>
    <truncated>0</truncated>
    <difficult>0</difficult>
    <bndbox>
      <xmin>158</xmin>
      <ymin>849</ymin>
      <xmax>226</xmax>
      <ymax>923</ymax>
    </bndbox>
  </object>
  <object>
    <name>all_Season_Road</name>
    <pose>Unspecified</pose>
    <truncated>0</truncated>
    <difficult>0</difficult>
    <bndbox>
      <xmin>499</xmin>
      <ymin>1131</ymin>
      <xmax>556</xmax>
      <ymax>1176</ymax>
    </bndbox>
  </object>
</annotation>
