<annotation>
  <folder>fullTrainingDataset/batch4</folder>
  <filename>000643.jpg</filename>
  <segmented>0</segmented>
  <size>
    <width>1200</width>
    <height>1050</height>
    <depth>3</depth>
  </size>
  <object>
    <name>all_Season_Road</name>
    <pose>Unspecified</pose>
    <truncated>0</truncated>
    <difficult>0</difficult>
    <bndbox>
      <xmin>5</xmin>
      <ymin>540</ymin>
      <xmax>361</xmax>
      <ymax>1042</ymax>
    </bndbox>
  </object>
  <object>
    <name>all_Season_Road</name>
    <pose>Unspecified</pose>
    <truncated>0</truncated>
    <difficult>0</difficult>
    <bndbox>
      <xmin>786</xmin>
      <ymin>434</ymin>
      <xmax>926</xmax>
      <ymax>599</ymax>
    </bndbox>
  </object>
</annotation>
