<annotation>
  <folder>fullTrainingDataset/batch4</folder>
  <filename>000763.jpg</filename>
  <segmented>0</segmented>
  <size>
    <width>675</width>
    <height>1200</height>
    <depth>3</depth>
  </size>
  <object>
    <name>all_Season_Road</name>
    <pose>Unspecified</pose>
    <truncated>0</truncated>
    <difficult>0</difficult>
    <bndbox>
      <xmin>401</xmin>
      <ymin>724</ymin>
      <xmax>670</xmax>
      <ymax>1166</ymax>
    </bndbox>
  </object>
  <object>
    <name>all_Season_Road</name>
    <pose>Unspecified</pose>
    <truncated>0</truncated>
    <difficult>0</difficult>
    <bndbox>
      <xmin>9</xmin>
      <ymin>957</ymin>
      <xmax>377</xmax>
      <ymax>1186</ymax>
    </bndbox>
  </object>
</annotation>
