<annotation>
  <folder>fullTrainingDataset/batch7</folder>
  <filename>001333.jpg</filename>
  <segmented>0</segmented>
  <size>
    <width>1200</width>
    <height>900</height>
    <depth>3</depth>
  </size>
  <object>
    <name>all_Season_Road</name>
    <pose>Unspecified</pose>
    <truncated>0</truncated>
    <difficult>0</difficult>
    <bndbox>
      <xmin>112</xmin>
      <ymin>601</ymin>
      <xmax>344</xmax>
      <ymax>895</ymax>
    </bndbox>
  </object>
  <object>
    <name>all_Season_Road</name>
    <pose>Unspecified</pose>
    <truncated>0</truncated>
    <difficult>0</difficult>
    <bndbox>
      <xmin>1</xmin>
      <ymin>628</ymin>
      <xmax>144</xmax>
      <ymax>897</ymax>
    </bndbox>
  </object>
  <object>
    <name>all_Season_Road</name>
    <pose>Unspecified</pose>
    <truncated>0</truncated>
    <difficult>0</difficult>
    <bndbox>
      <xmin>286</xmin>
      <ymin>583</ymin>
      <xmax>352</xmax>
      <ymax>613</ymax>
    </bndbox>
  </object>
  <object>
    <name>all_Season_Road</name>
    <pose>Unspecified</pose>
    <truncated>0</truncated>
    <difficult>0</difficult>
    <bndbox>
      <xmin>230</xmin>
      <ymin>588</ymin>
      <xmax>276</xmax>
      <ymax>621</ymax>
    </bndbox>
  </object>
</annotation>
