<annotation>
  <folder>fullTrainingDataset/batch9</folder>
  <filename>001640.jpg</filename>
  <segmented>0</segmented>
  <size>
    <width>900</width>
    <height>1200</height>
    <depth>3</depth>
  </size>
  <object>
    <name>all_Season_Road</name>
    <pose>Unspecified</pose>
    <truncated>0</truncated>
    <difficult>0</difficult>
    <bndbox>
      <xmin>192</xmin>
      <ymin>1063</ymin>
      <xmax>875</xmax>
      <ymax>1191</ymax>
    </bndbox>
  </object>
  <object>
    <name>all_Season_Road</name>
    <pose>Unspecified</pose>
    <truncated>0</truncated>
    <difficult>0</difficult>
    <bndbox>
      <xmin>432</xmin>
      <ymin>1017</ymin>
      <xmax>690</xmax>
      <ymax>1198</ymax>
    </bndbox>
  </object>
</annotation>
