<annotation>
  <folder>fullTrainingDataset/batch10</folder>
  <filename>001909.jpg</filename>
  <segmented>0</segmented>
  <size>
    <width>1200</width>
    <height>918</height>
    <depth>3</depth>
  </size>
  <object>
    <name>all_Season_Road</name>
    <pose>Unspecified</pose>
    <truncated>0</truncated>
    <difficult>0</difficult>
    <bndbox>
      <xmin>120</xmin>
      <ymin>582</ymin>
      <xmax>1197</xmax>
      <ymax>909</ymax>
    </bndbox>
  </object>
  <object>
    <name>all_Season_Road</name>
    <pose>Unspecified</pose>
    <truncated>0</truncated>
    <difficult>0</difficult>
    <bndbox>
      <xmin>1</xmin>
      <ymin>610</ymin>
      <xmax>151</xmax>
      <ymax>915</ymax>
    </bndbox>
  </object>
</annotation>
