<annotation>
  <folder>fullTrainingDataset/batch10</folder>
  <filename>001992.jpg</filename>
  <segmented>0</segmented>
  <size>
    <width>720</width>
    <height>406</height>
    <depth>3</depth>
  </size>
  <object>
    <name>all_Season_Road</name>
    <pose>Unspecified</pose>
    <truncated>0</truncated>
    <difficult>0</difficult>
    <bndbox>
      <xmin>29</xmin>
      <ymin>323</ymin>
      <xmax>633</xmax>
      <ymax>403</ymax>
    </bndbox>
  </object>
  <object>
    <name>all_Season_Road</name>
    <pose>Unspecified</pose>
    <truncated>0</truncated>
    <difficult>0</difficult>
    <bndbox>
      <xmin>616</xmin>
      <ymin>315</ymin>
      <xmax>649</xmax>
      <ymax>335</ymax>
    </bndbox>
  </object>
  <object>
    <name>all_Season_Road</name>
    <pose>Unspecified</pose>
    <truncated>0</truncated>
    <difficult>0</difficult>
    <bndbox>
      <xmin>666</xmin>
      <ymin>316</ymin>
      <xmax>719</xmax>
      <ymax>328</ymax>
    </bndbox>
  </object>
</annotation>
