<annotation>
  <folder>fullTrainingDataset/batch11</folder>
  <filename>002192.jpg</filename>
  <segmented>0</segmented>
  <size>
    <width>640</width>
    <height>640</height>
    <depth>3</depth>
  </size>
  <object>
    <name>all_Season_Road</name>
    <pose>Unspecified</pose>
    <truncated>0</truncated>
    <difficult>0</difficult>
    <bndbox>
      <xmin>4</xmin>
      <ymin>465</ymin>
      <xmax>471</xmax>
      <ymax>615</ymax>
    </bndbox>
  </object>
  <object>
    <name>all_Season_Road</name>
    <pose>Unspecified</pose>
    <truncated>0</truncated>
    <difficult>0</difficult>
    <bndbox>
      <xmin>106</xmin>
      <ymin>431</ymin>
      <xmax>426</xmax>
      <ymax>525</ymax>
    </bndbox>
  </object>
  <object>
    <name>all_Season_Road</name>
    <pose>Unspecified</pose>
    <truncated>0</truncated>
    <difficult>0</difficult>
    <bndbox>
      <xmin>186</xmin>
      <ymin>386</ymin>
      <xmax>405</xmax>
      <ymax>470</ymax>
    </bndbox>
  </object>
  <object>
    <name>all_Season_Road</name>
    <pose>Unspecified</pose>
    <truncated>0</truncated>
    <difficult>0</difficult>
    <bndbox>
      <xmin>261</xmin>
      <ymin>362</ymin>
      <xmax>369</xmax>
      <ymax>407</ymax>
    </bndbox>
  </object>
  <object>
    <name>all_Season_Road</name>
    <pose>Unspecified</pose>
    <truncated>0</truncated>
    <difficult>0</difficult>
    <bndbox>
      <xmin>311</xmin>
      <ymin>333</ymin>
      <xmax>361</xmax>
      <ymax>372</ymax>
    </bndbox>
  </object>
</annotation>
