<annotation>
  <folder>fullTrainingDataset/batch11</folder>
  <filename>002115.jpg</filename>
  <segmented>0</segmented>
  <size>
    <width>675</width>
    <height>1200</height>
    <depth>3</depth>
  </size>
  <object>
    <name>all_Season_Road</name>
    <pose>Unspecified</pose>
    <truncated>0</truncated>
    <difficult>0</difficult>
    <bndbox>
      <xmin>23</xmin>
      <ymin>262</ymin>
      <xmax>539</xmax>
      <ymax>559</ymax>
    </bndbox>
  </object>
  <object>
    <name>all_Season_Road</name>
    <pose>Unspecified</pose>
    <truncated>0</truncated>
    <difficult>0</difficult>
    <bndbox>
      <xmin>0</xmin>
      <ymin>375</ymin>
      <xmax>411</xmax>
      <ymax>671</ymax>
    </bndbox>
  </object>
  <object>
    <name>all_Season_Road</name>
    <pose>Unspecified</pose>
    <truncated>0</truncated>
    <difficult>0</difficult>
    <bndbox>
      <xmin>0</xmin>
      <ymin>505</ymin>
      <xmax>279</xmax>
      <ymax>801</ymax>
    </bndbox>
  </object>
  <object>
    <name>all_Season_Road</name>
    <pose>Unspecified</pose>
    <truncated>0</truncated>
    <difficult>0</difficult>
    <bndbox>
      <xmin>0</xmin>
      <ymin>635</ymin>
      <xmax>192</xmax>
      <ymax>931</ymax>
    </bndbox>
  </object>
  <object>
    <name>all_Season_Road</name>
    <pose>Unspecified</pose>
    <truncated>0</truncated>
    <difficult>0</difficult>
    <bndbox>
      <xmin>0</xmin>
      <ymin>963</ymin>
      <xmax>97</xmax>
      <ymax>1199</ymax>
    </bndbox>
  </object>
</annotation>
