<annotation>
  <folder>fullTrainingDataset/batch12</folder>
  <filename>002296.jpg</filename>
  <segmented>0</segmented>
  <size>
    <width>900</width>
    <height>1200</height>
    <depth>3</depth>
  </size>
  <object>
    <name>all_Season_Road</name>
    <pose>Unspecified</pose>
    <truncated>0</truncated>
    <difficult>0</difficult>
    <bndbox>
      <xmin>392</xmin>
      <ymin>411</ymin>
      <xmax>479</xmax>
      <ymax>505</ymax>
    </bndbox>
  </object>
  <object>
    <name>all_Season_Road</name>
    <pose>Unspecified</pose>
    <truncated>0</truncated>
    <difficult>0</difficult>
    <bndbox>
      <xmin>303</xmin>
      <ymin>424</ymin>
      <xmax>390</xmax>
      <ymax>517</ymax>
    </bndbox>
  </object>
  <object>
    <name>all_Season_Road</name>
    <pose>Unspecified</pose>
    <truncated>0</truncated>
    <difficult>0</difficult>
    <bndbox>
      <xmin>206</xmin>
      <ymin>456</ymin>
      <xmax>294</xmax>
      <ymax>549</ymax>
    </bndbox>
  </object>
  <object>
    <name>all_Season_Road</name>
    <pose>Unspecified</pose>
    <truncated>0</truncated>
    <difficult>0</difficult>
    <bndbox>
      <xmin>501</xmin>
      <ymin>430</ymin>
      <xmax>589</xmax>
      <ymax>524</ymax>
    </bndbox>
  </object>
  <object>
    <name>all_Season_Road</name>
    <pose>Unspecified</pose>
    <truncated>0</truncated>
    <difficult>0</difficult>
    <bndbox>
      <xmin>579</xmin>
      <ymin>422</ymin>
      <xmax>666</xmax>
      <ymax>516</ymax>
    </bndbox>
  </object>
</annotation>
