<annotation>
  <folder>fullTrainingDataset/batch13</folder>
  <filename>002541.jpg</filename>
  <segmented>0</segmented>
  <size>
    <width>900</width>
    <height>1200</height>
    <depth>3</depth>
  </size>
  <object>
    <name>all_Season_Road</name>
    <pose>Unspecified</pose>
    <truncated>0</truncated>
    <difficult>0</difficult>
    <bndbox>
      <xmin>8</xmin>
      <ymin>728</ymin>
      <xmax>363</xmax>
      <ymax>1196</ymax>
    </bndbox>
  </object>
  <object>
    <name>all_Season_Road</name>
    <pose>Unspecified</pose>
    <truncated>0</truncated>
    <difficult>0</difficult>
    <bndbox>
      <xmin>321</xmin>
      <ymin>985</ymin>
      <xmax>498</xmax>
      <ymax>1190</ymax>
    </bndbox>
  </object>
  <object>
    <name>all_Season_Road</name>
    <pose>Unspecified</pose>
    <truncated>0</truncated>
    <difficult>0</difficult>
    <bndbox>
      <xmin>777</xmin>
      <ymin>911</ymin>
      <xmax>890</xmax>
      <ymax>1198</ymax>
    </bndbox>
  </object>
  <object>
    <name>all_Season_Road</name>
    <pose>Unspecified</pose>
    <truncated>0</truncated>
    <difficult>0</difficult>
    <bndbox>
      <xmin>2</xmin>
      <ymin>340</ymin>
      <xmax>108</xmax>
      <ymax>1190</ymax>
    </bndbox>
  </object>
</annotation>
