<annotation>
  <folder>fullTrainingDataset/batch14</folder>
  <filename>002662.jpg</filename>
  <segmented>0</segmented>
  <size>
    <width>1200</width>
    <height>902</height>
    <depth>3</depth>
  </size>
  <object>
    <name>all_Season_Road</name>
    <pose>Unspecified</pose>
    <truncated>0</truncated>
    <difficult>0</difficult>
    <bndbox>
      <xmin>678</xmin>
      <ymin>584</ymin>
      <xmax>1194</xmax>
      <ymax>895</ymax>
    </bndbox>
  </object>
  <object>
    <name>all_Season_Road</name>
    <pose>Unspecified</pose>
    <truncated>0</truncated>
    <difficult>0</difficult>
    <bndbox>
      <xmin>899</xmin>
      <ymin>511</ymin>
      <xmax>1197</xmax>
      <ymax>900</ymax>
    </bndbox>
  </object>
</annotation>
