<annotation>
  <folder>fullTrainingDataset/batch15</folder>
  <filename>002929.jpg</filename>
  <segmented>0</segmented>
  <size>
    <width>675</width>
    <height>1200</height>
    <depth>3</depth>
  </size>
  <object>
    <name>all_Season_Road</name>
    <pose>Unspecified</pose>
    <truncated>0</truncated>
    <difficult>0</difficult>
    <bndbox>
      <xmin>10</xmin>
      <ymin>657</ymin>
      <xmax>427</xmax>
      <ymax>1169</ymax>
    </bndbox>
  </object>
  <object>
    <name>all_Season_Road</name>
    <pose>Unspecified</pose>
    <truncated>0</truncated>
    <difficult>0</difficult>
    <bndbox>
      <xmin>390</xmin>
      <ymin>800</ymin>
      <xmax>673</xmax>
      <ymax>1133</ymax>
    </bndbox>
  </object>
</annotation>
