<annotation>
  <folder>fullTrainingDataset/batch16</folder>
  <filename>003053.jpg</filename>
  <segmented>0</segmented>
  <size>
    <width>1200</width>
    <height>900</height>
    <depth>3</depth>
  </size>
  <object>
    <name>all_Season_Road</name>
    <pose>Unspecified</pose>
    <truncated>0</truncated>
    <difficult>0</difficult>
    <bndbox>
      <xmin>570</xmin>
      <ymin>766</ymin>
      <xmax>658</xmax>
      <ymax>892</ymax>
    </bndbox>
  </object>
  <object>
    <name>all_Season_Road</name>
    <pose>Unspecified</pose>
    <truncated>0</truncated>
    <difficult>0</difficult>
    <bndbox>
      <xmin>636</xmin>
      <ymin>811</ymin>
      <xmax>727</xmax>
      <ymax>891</ymax>
    </bndbox>
  </object>
</annotation>
