<annotation>
  <folder>fullTrainingDataset/batch18</folder>
  <filename>003483.jpg</filename>
  <segmented>0</segmented>
  <size>
    <width>352</width>
    <height>288</height>
    <depth>3</depth>
  </size>
  <object>
    <name>all_Season_Road</name>
    <pose>Unspecified</pose>
    <truncated>0</truncated>
    <difficult>0</difficult>
    <bndbox>
      <xmin>47</xmin>
      <ymin>182</ymin>
      <xmax>272</xmax>
      <ymax>236</ymax>
    </bndbox>
  </object>
  <object>
    <name>all_Season_Road</name>
    <pose>Unspecified</pose>
    <truncated>0</truncated>
    <difficult>0</difficult>
    <bndbox>
      <xmin>45</xmin>
      <ymin>131</ymin>
      <xmax>189</xmax>
      <ymax>258</ymax>
    </bndbox>
  </object>
  <object>
    <name>all_Season_Road</name>
    <pose>Unspecified</pose>
    <truncated>0</truncated>
    <difficult>0</difficult>
    <bndbox>
      <xmin>278</xmin>
      <ymin>149</ymin>
      <xmax>312</xmax>
      <ymax>186</ymax>
    </bndbox>
  </object>
</annotation>
