<annotation>
  <folder>fullTrainingDataset/batch18</folder>
  <filename>003472.jpg</filename>
  <segmented>0</segmented>
  <size>
    <width>1159</width>
    <height>548</height>
    <depth>3</depth>
  </size>
  <object>
    <name>all_Season_Road</name>
    <pose>Unspecified</pose>
    <truncated>0</truncated>
    <difficult>0</difficult>
    <bndbox>
      <xmin>610</xmin>
      <ymin>414</ymin>
      <xmax>758</xmax>
      <ymax>543</ymax>
    </bndbox>
  </object>
  <object>
    <name>all_Season_Road</name>
    <pose>Unspecified</pose>
    <truncated>0</truncated>
    <difficult>0</difficult>
    <bndbox>
      <xmin>811</xmin>
      <ymin>473</ymin>
      <xmax>959</xmax>
      <ymax>547</ymax>
    </bndbox>
  </object>
  <object>
    <name>all_Season_Road</name>
    <pose>Unspecified</pose>
    <truncated>0</truncated>
    <difficult>0</difficult>
    <bndbox>
      <xmin>526</xmin>
      <ymin>351</ymin>
      <xmax>624</xmax>
      <ymax>407</ymax>
    </bndbox>
  </object>
  <object>
    <name>all_Season_Road</name>
    <pose>Unspecified</pose>
    <truncated>0</truncated>
    <difficult>0</difficult>
    <bndbox>
      <xmin>307</xmin>
      <ymin>482</ymin>
      <xmax>511</xmax>
      <ymax>544</ymax>
    </bndbox>
  </object>
</annotation>
