<annotation>
  <folder>fullTrainingDataset/batch19</folder>
  <filename>003659.jpg</filename>
  <segmented>0</segmented>
  <size>
    <width>900</width>
    <height>1200</height>
    <depth>3</depth>
  </size>
  <object>
    <name>all_Season_Road</name>
    <pose>Unspecified</pose>
    <truncated>0</truncated>
    <difficult>0</difficult>
    <bndbox>
      <xmin>5</xmin>
      <ymin>922</ymin>
      <xmax>286</xmax>
      <ymax>1198</ymax>
    </bndbox>
  </object>
  <object>
    <name>all_Season_Road</name>
    <pose>Unspecified</pose>
    <truncated>0</truncated>
    <difficult>0</difficult>
    <bndbox>
      <xmin>248</xmin>
      <ymin>1047</ymin>
      <xmax>883</xmax>
      <ymax>1196</ymax>
    </bndbox>
  </object>
  <object>
    <name>all_Season_Road</name>
    <pose>Unspecified</pose>
    <truncated>0</truncated>
    <difficult>0</difficult>
    <bndbox>
      <xmin>512</xmin>
      <ymin>920</ymin>
      <xmax>658</xmax>
      <ymax>1196</ymax>
    </bndbox>
  </object>
  <object>
    <name>all_Season_Road</name>
    <pose>Unspecified</pose>
    <truncated>0</truncated>
    <difficult>0</difficult>
    <bndbox>
      <xmin>715</xmin>
      <ymin>920</ymin>
      <xmax>896</xmax>
      <ymax>1068</ymax>
    </bndbox>
  </object>
</annotation>
