<annotation>
  <folder>fullTrainingDataset/batch21</folder>
  <filename>004126.jpg</filename>
  <segmented>0</segmented>
  <size>
    <width>512</width>
    <height>512</height>
    <depth>3</depth>
  </size>
  <object>
    <name>all_Season_Road</name>
    <pose>Unspecified</pose>
    <truncated>0</truncated>
    <difficult>0</difficult>
    <bndbox>
      <xmin>3</xmin>
      <ymin>408</ymin>
      <xmax>200</xmax>
      <ymax>509</ymax>
    </bndbox>
  </object>
  <object>
    <name>all_Season_Road</name>
    <pose>Unspecified</pose>
    <truncated>0</truncated>
    <difficult>0</difficult>
    <bndbox>
      <xmin>64</xmin>
      <ymin>358</ymin>
      <xmax>145</xmax>
      <ymax>506</ymax>
    </bndbox>
  </object>
  <object>
    <name>all_Season_Road</name>
    <pose>Unspecified</pose>
    <truncated>0</truncated>
    <difficult>0</difficult>
    <bndbox>
      <xmin>103</xmin>
      <ymin>315</ymin>
      <xmax>129</xmax>
      <ymax>431</ymax>
    </bndbox>
  </object>
</annotation>
