<annotation>
  <folder>fullTrainingDataset/batch23</folder>
  <filename>004484.jpg</filename>
  <segmented>0</segmented>
  <size>
    <width>1024</width>
    <height>768</height>
    <depth>3</depth>
  </size>
  <object>
    <name>all_Season_Road</name>
    <pose>Unspecified</pose>
    <truncated>0</truncated>
    <difficult>0</difficult>
    <bndbox>
      <xmin>234</xmin>
      <ymin>272</ymin>
      <xmax>526</xmax>
      <ymax>766</ymax>
    </bndbox>
  </object>
  <object>
    <name>all_Season_Road</name>
    <pose>Unspecified</pose>
    <truncated>0</truncated>
    <difficult>0</difficult>
    <bndbox>
      <xmin>320</xmin>
      <ymin>302</ymin>
      <xmax>612</xmax>
      <ymax>767</ymax>
    </bndbox>
  </object>
  <object>
    <name>all_Season_Road</name>
    <pose>Unspecified</pose>
    <truncated>0</truncated>
    <difficult>0</difficult>
    <bndbox>
      <xmin>495</xmin>
      <ymin>310</ymin>
      <xmax>787</xmax>
      <ymax>767</ymax>
    </bndbox>
  </object>
  <object>
    <name>all_Season_Road</name>
    <pose>Unspecified</pose>
    <truncated>0</truncated>
    <difficult>0</difficult>
    <bndbox>
      <xmin>664</xmin>
      <ymin>368</ymin>
      <xmax>956</xmax>
      <ymax>767</ymax>
    </bndbox>
  </object>
  <object>
    <name>all_Season_Road</name>
    <pose>Unspecified</pose>
    <truncated>0</truncated>
    <difficult>0</difficult>
    <bndbox>
      <xmin>749</xmin>
      <ymin>389</ymin>
      <xmax>1023</xmax>
      <ymax>767</ymax>
    </bndbox>
  </object>
</annotation>
