<annotation>
  <folder>fullTrainingDataset/batch24</folder>
  <filename>004693.jpg</filename>
  <segmented>0</segmented>
  <size>
    <width>1024</width>
    <height>576</height>
    <depth>3</depth>
  </size>
  <object>
    <name>all_Season_Road</name>
    <pose>Unspecified</pose>
    <truncated>0</truncated>
    <difficult>0</difficult>
    <bndbox>
      <xmin>411</xmin>
      <ymin>545</ymin>
      <xmax>592</xmax>
      <ymax>572</ymax>
    </bndbox>
  </object>
  <object>
    <name>all_Season_Road</name>
    <pose>Unspecified</pose>
    <truncated>0</truncated>
    <difficult>0</difficult>
    <bndbox>
      <xmin>469</xmin>
      <ymin>521</ymin>
      <xmax>521</xmax>
      <ymax>573</ymax>
    </bndbox>
  </object>
  <object>
    <name>all_Season_Road</name>
    <pose>Unspecified</pose>
    <truncated>0</truncated>
    <difficult>0</difficult>
    <bndbox>
      <xmin>502</xmin>
      <ymin>509</ymin>
      <xmax>523</xmax>
      <ymax>574</ymax>
    </bndbox>
  </object>
</annotation>
