<annotation>
  <folder>fullTrainingDataset/batch24</folder>
  <filename>004712.jpg</filename>
  <segmented>0</segmented>
  <size>
    <width>1200</width>
    <height>900</height>
    <depth>3</depth>
  </size>
  <object>
    <name>all_Season_Road</name>
    <pose>Unspecified</pose>
    <truncated>0</truncated>
    <difficult>0</difficult>
    <bndbox>
      <xmin>444</xmin>
      <ymin>717</ymin>
      <xmax>585</xmax>
      <ymax>833</ymax>
    </bndbox>
  </object>
  <object>
    <name>all_Season_Road</name>
    <pose>Unspecified</pose>
    <truncated>0</truncated>
    <difficult>0</difficult>
    <bndbox>
      <xmin>877</xmin>
      <ymin>707</ymin>
      <xmax>1128</xmax>
      <ymax>892</ymax>
    </bndbox>
  </object>
  <object>
    <name>all_Season_Road</name>
    <pose>Unspecified</pose>
    <truncated>0</truncated>
    <difficult>0</difficult>
    <bndbox>
      <xmin>523</xmin>
      <ymin>601</ymin>
      <xmax>574</xmax>
      <ymax>887</ymax>
    </bndbox>
  </object>
  <object>
    <name>all_Season_Road</name>
    <pose>Unspecified</pose>
    <truncated>0</truncated>
    <difficult>0</difficult>
    <bndbox>
      <xmin>1</xmin>
      <ymin>780</ymin>
      <xmax>84</xmax>
      <ymax>897</ymax>
    </bndbox>
  </object>
</annotation>
