<annotation>
  <folder>fullTrainingDataset/batch25</folder>
  <filename>004804.jpg</filename>
  <segmented>0</segmented>
  <size>
    <width>900</width>
    <height>1200</height>
    <depth>3</depth>
  </size>
  <object>
    <name>all_Season_Road</name>
    <pose>Unspecified</pose>
    <truncated>0</truncated>
    <difficult>0</difficult>
    <bndbox>
      <xmin>4</xmin>
      <ymin>835</ymin>
      <xmax>896</xmax>
      <ymax>1196</ymax>
    </bndbox>
  </object>
  <object>
    <name>all_Season_Road</name>
    <pose>Unspecified</pose>
    <truncated>0</truncated>
    <difficult>0</difficult>
    <bndbox>
      <xmin>4</xmin>
      <ymin>736</ymin>
      <xmax>893</xmax>
      <ymax>765</ymax>
    </bndbox>
  </object>
  <object>
    <name>all_Season_Road</name>
    <pose>Unspecified</pose>
    <truncated>0</truncated>
    <difficult>0</difficult>
    <bndbox>
      <xmin>45</xmin>
      <ymin>674</ymin>
      <xmax>446</xmax>
      <ymax>719</ymax>
    </bndbox>
  </object>
  <object>
    <name>all_Season_Road</name>
    <pose>Unspecified</pose>
    <truncated>0</truncated>
    <difficult>0</difficult>
    <bndbox>
      <xmin>478</xmin>
      <ymin>671</ymin>
      <xmax>837</xmax>
      <ymax>708</ymax>
    </bndbox>
  </object>
</annotation>
